odoo/addons/document_page_environmental_aspect/README.rst
odoo/addons/document_page_environmental_aspect/__init__.py
odoo/addons/document_page_environmental_aspect/__manifest__.py
odoo/addons/document_page_environmental_aspect/data/document_page.xml
odoo/addons/document_page_environmental_aspect/i18n/de.po
odoo/addons/document_page_environmental_aspect/i18n/document_page_environmental_aspect.pot
odoo/addons/document_page_environmental_aspect/i18n/es.po
odoo/addons/document_page_environmental_aspect/i18n/es_CL.po
odoo/addons/document_page_environmental_aspect/i18n/fa.po
odoo/addons/document_page_environmental_aspect/i18n/fr.po
odoo/addons/document_page_environmental_aspect/i18n/it.po
odoo/addons/document_page_environmental_aspect/i18n/nb.po
odoo/addons/document_page_environmental_aspect/i18n/pt.po
odoo/addons/document_page_environmental_aspect/i18n/pt_BR.po
odoo/addons/document_page_environmental_aspect/i18n/sl.po
odoo/addons/document_page_environmental_aspect/i18n/sv.po
odoo/addons/document_page_environmental_aspect/i18n/vi.po
odoo/addons/document_page_environmental_aspect/readme/CONFIGURE.md
odoo/addons/document_page_environmental_aspect/readme/CONTRIBUTORS.md
odoo/addons/document_page_environmental_aspect/readme/DESCRIPTION.md
odoo/addons/document_page_environmental_aspect/readme/USAGE.md
odoo/addons/document_page_environmental_aspect/static/description/icon.png
odoo/addons/document_page_environmental_aspect/static/description/index.html
odoo/addons/document_page_environmental_aspect/views/document_page.xml
odoo_addon_document_page_environmental_aspect-18.0.1.0.1.dist-info/METADATA
odoo_addon_document_page_environmental_aspect-18.0.1.0.1.dist-info/WHEEL
odoo_addon_document_page_environmental_aspect-18.0.1.0.1.dist-info/top_level.txt
odoo_addon_document_page_environmental_aspect-18.0.1.0.1.dist-info/RECORD
